torext/__init__.py
torext/app.py
torext/base_settings.py
torext/compat.py
torext/errors.py
torext/gevent_wsgi.py
torext/log.py
torext/make_settings.py
torext/params.py
torext/route.py
torext/script.py
torext/sql.py
torext/testing.py
torext/utils.py
torext/handlers/__init__.py
torext/handlers/base.py
torext/handlers/oauth.py
torext/scripts/__init__.py
torext/scripts/sketch.py
torext/templates/project/__init__.py
torext/templates/project/app.py
torext/templates/project/settings.py
torext/test/__init__.py
torext/test/handlers_base_test.py
torext/test/jinja2_test.py
torext/test/log_test.py
torext/test/params_test.py
torext/test/route_test.py
torext/test/script_test.py
torext/test/sql_test.py
torext/test/testing_test.py
torext/test/utils_test.py
torext-0.10.0.dist-info/DESCRIPTION.rst
torext-0.10.0.dist-info/METADATA
torext-0.10.0.dist-info/RECORD
torext-0.10.0.dist-info/WHEEL
torext-0.10.0.dist-info/entry_points.txt
torext-0.10.0.dist-info/metadata.json
torext-0.10.0.dist-info/top_level.txt
