Metadata-Version: 2.0
Name: torext
Version: 0.10.0
Summary: The missing tornado mate
Home-page: http://github.com/reorx/torext
Author: reorx
Author-email: novoreorx@gmail.com
License: License :: OSI Approved :: MIT License
Platform: UNKNOWN
Requires-Dist: tornado (==3.0)
Provides-Extra: gevent
Requires-Dist: gevent; extra == 'gevent'
Provides-Extra: sql
Requires-Dist: SQLAlchemy; extra == 'sql'
